{"nodes": [{"id": "c_users_asus_desktop_doklynk_doklynk_web_src_components_postcard_tsx", "label": "PostCard.tsx", "file_type": "code", "source_file": "C:\\Users\\ASUS\\Desktop\\DokLynk\\DokLynk Web\\src\\components\\PostCard.tsx", "source_location": "L1"}, {"id": "components_postcard_postcard", "label": "PostCard()", "file_type": "code", "source_file": "C:\\Users\\ASUS\\Desktop\\DokLynk\\DokLynk Web\\src\\components\\PostCard.tsx", "source_location": "L28"}, {"id": "components_postcard_rendercontent", "label": "renderContent()", "file_type": "code", "source_file": "C:\\Users\\ASUS\\Desktop\\DokLynk\\DokLynk Web\\src\\components\\PostCard.tsx", "source_location": "L340"}], "edges": [{"source": "c_users_asus_desktop_doklynk_doklynk_web_src_components_postcard_tsx", "target": "react", "relation": "imports_from", "context": "import", "confidence": "EXTRACTED", "source_file": "C:\\Users\\ASUS\\Desktop\\DokLynk\\DokLynk Web\\src\\components\\PostCard.tsx", "source_location": "L2", "weight": 1.0}, {"source": "c_users_asus_desktop_doklynk_doklynk_web_src_components_postcard_tsx", "target": "c_users_asus_desktop_doklynk_doklynk_web_src_lib_router_tsx", "relation": "imports_from", "context": "import", "confidence": "EXTRACTED", "source_file": "C:\\Users\\ASUS\\Desktop\\DokLynk\\DokLynk Web\\src\\components\\PostCard.tsx", "source_location": "L3", "weight": 1.0}, {"source": "c_users_asus_desktop_doklynk_doklynk_web_src_components_postcard_tsx", "target": "lib_router_usenavigate", "relation": "imports", "context": "import", "confidence": "EXTRACTED", "source_file": "C:\\Users\\ASUS\\Desktop\\DokLynk\\DokLynk Web\\src\\components\\PostCard.tsx", "source_location": "L3", "weight": 1.0}, {"source": "c_users_asus_desktop_doklynk_doklynk_web_src_components_postcard_tsx", "target": "lucide_react", "relation": "imports_from", "context": "import", "confidence": "EXTRACTED", "source_file": "C:\\Users\\ASUS\\Desktop\\DokLynk\\DokLynk Web\\src\\components\\PostCard.tsx", "source_location": "L4", "weight": 1.0}, {"source": "c_users_asus_desktop_doklynk_doklynk_web_src_components_postcard_tsx", "target": "c_users_asus_desktop_doklynk_doklynk_web_src_components_ui_primitives_tsx", "relation": "imports_from", "context": "import", "confidence": "EXTRACTED", "source_file": "C:\\Users\\ASUS\\Desktop\\DokLynk\\DokLynk Web\\src\\components\\PostCard.tsx", "source_location": "L8", "weight": 1.0}, {"source": "c_users_asus_desktop_doklynk_doklynk_web_src_components_postcard_tsx", "target": "ui_primitives_avatar", "relation": "imports", "context": "import", "confidence": "EXTRACTED", "source_file": "C:\\Users\\ASUS\\Desktop\\DokLynk\\DokLynk Web\\src\\components\\PostCard.tsx", "source_location": "L8", "weight": 1.0}, {"source": "c_users_asus_desktop_doklynk_doklynk_web_src_components_postcard_tsx", "target": "ui_primitives_verified", "relation": "imports", "context": "import", "confidence": "EXTRACTED", "source_file": "C:\\Users\\ASUS\\Desktop\\DokLynk\\DokLynk Web\\src\\components\\PostCard.tsx", "source_location": "L8", "weight": 1.0}, {"source": "c_users_asus_desktop_doklynk_doklynk_web_src_components_postcard_tsx", "target": "ui_primitives_posttypebadge", "relation": "imports", "context": "import", "confidence": "EXTRACTED", "source_file": "C:\\Users\\ASUS\\Desktop\\DokLynk\\DokLynk Web\\src\\components\\PostCard.tsx", "source_location": "L8", "weight": 1.0}, {"source": "c_users_asus_desktop_doklynk_doklynk_web_src_components_postcard_tsx", "target": "c_users_asus_desktop_doklynk_doklynk_web_src_components_ui_reactionbutton_tsx", "relation": "imports_from", "context": "import", "confidence": "EXTRACTED", "source_file": "C:\\Users\\ASUS\\Desktop\\DokLynk\\DokLynk Web\\src\\components\\PostCard.tsx", "source_location": "L9", "weight": 1.0}, {"source": "c_users_asus_desktop_doklynk_doklynk_web_src_components_postcard_tsx", "target": "ui_reactionbutton_reactions", "relation": "imports", "context": "import", "confidence": "EXTRACTED", "source_file": "C:\\Users\\ASUS\\Desktop\\DokLynk\\DokLynk Web\\src\\components\\PostCard.tsx", "source_location": "L9", "weight": 1.0}, {"source": "c_users_asus_desktop_doklynk_doklynk_web_src_components_postcard_tsx", "target": "c_users_asus_desktop_doklynk_doklynk_web_src_components_ui_followbutton_tsx", "relation": "imports_from", "context": "import", "confidence": "EXTRACTED", "source_file": "C:\\Users\\ASUS\\Desktop\\DokLynk\\DokLynk Web\\src\\components\\PostCard.tsx", "source_location": "L10", "weight": 1.0}, {"source": "c_users_asus_desktop_doklynk_doklynk_web_src_components_postcard_tsx", "target": "c_users_asus_desktop_doklynk_doklynk_web_src_components_ui_overlays_tsx", "relation": "imports_from", "context": "import", "confidence": "EXTRACTED", "source_file": "C:\\Users\\ASUS\\Desktop\\DokLynk\\DokLynk Web\\src\\components\\PostCard.tsx", "source_location": "L11", "weight": 1.0}, {"source": "c_users_asus_desktop_doklynk_doklynk_web_src_components_postcard_tsx", "target": "ui_overlays_bottomsheet", "relation": "imports", "context": "import", "confidence": "EXTRACTED", "source_file": "C:\\Users\\ASUS\\Desktop\\DokLynk\\DokLynk Web\\src\\components\\PostCard.tsx", "source_location": "L11", "weight": 1.0}, {"source": "c_users_asus_desktop_doklynk_doklynk_web_src_components_postcard_tsx", "target": "ui_overlays_sheetrow", "relation": "imports", "context": "import", "confidence": "EXTRACTED", "source_file": "C:\\Users\\ASUS\\Desktop\\DokLynk\\DokLynk Web\\src\\components\\PostCard.tsx", "source_location": "L11", "weight": 1.0}, {"source": "c_users_asus_desktop_doklynk_doklynk_web_src_components_postcard_tsx", "target": "ui_overlays_modal", "relation": "imports", "context": "import", "confidence": "EXTRACTED", "source_file": "C:\\Users\\ASUS\\Desktop\\DokLynk\\DokLynk Web\\src\\components\\PostCard.tsx", "source_location": "L11", "weight": 1.0}, {"source": "c_users_asus_desktop_doklynk_doklynk_web_src_components_postcard_tsx", "target": "c_users_asus_desktop_doklynk_doklynk_web_src_components_sharesheet_tsx", "relation": "imports_from", "context": "import", "confidence": "EXTRACTED", "source_file": "C:\\Users\\ASUS\\Desktop\\DokLynk\\DokLynk Web\\src\\components\\PostCard.tsx", "source_location": "L12", "weight": 1.0}, {"source": "c_users_asus_desktop_doklynk_doklynk_web_src_components_postcard_tsx", "target": "c_users_asus_desktop_doklynk_doklynk_web_src_components_likessheet_tsx", "relation": "imports_from", "context": "import", "confidence": "EXTRACTED", "source_file": "C:\\Users\\ASUS\\Desktop\\DokLynk\\DokLynk Web\\src\\components\\PostCard.tsx", "source_location": "L13", "weight": 1.0}, {"source": "c_users_asus_desktop_doklynk_doklynk_web_src_components_postcard_tsx", "target": "c_users_asus_desktop_doklynk_doklynk_web_src_components_commentssheet_tsx", "relation": "imports_from", "context": "import", "confidence": "EXTRACTED", "source_file": "C:\\Users\\ASUS\\Desktop\\DokLynk\\DokLynk Web\\src\\components\\PostCard.tsx", "source_location": "L14", "weight": 1.0}, {"source": "c_users_asus_desktop_doklynk_doklynk_web_src_components_postcard_tsx", "target": "c_users_asus_desktop_doklynk_doklynk_web_src_components_reportsheet_tsx", "relation": "imports_from", "context": "import", "confidence": "EXTRACTED", "source_file": "C:\\Users\\ASUS\\Desktop\\DokLynk\\DokLynk Web\\src\\components\\PostCard.tsx", "source_location": "L15", "weight": 1.0}, {"source": "c_users_asus_desktop_doklynk_doklynk_web_src_components_postcard_tsx", "target": "c_users_asus_desktop_doklynk_doklynk_web_src_components_editpostmodal_tsx", "relation": "imports_from", "context": "import", "confidence": "EXTRACTED", "source_file": "C:\\Users\\ASUS\\Desktop\\DokLynk\\DokLynk Web\\src\\components\\PostCard.tsx", "source_location": "L16", "weight": 1.0}, {"source": "c_users_asus_desktop_doklynk_doklynk_web_src_components_postcard_tsx", "target": "components_editpostmodal_caneditpost", "relation": "imports", "context": "import", "confidence": "EXTRACTED", "source_file": "C:\\Users\\ASUS\\Desktop\\DokLynk\\DokLynk Web\\src\\components\\PostCard.tsx", "source_location": "L16", "weight": 1.0}, {"source": "c_users_asus_desktop_doklynk_doklynk_web_src_components_postcard_tsx", "target": "c_users_asus_desktop_doklynk_doklynk_web_src_context_authcontext_tsx", "relation": "imports_from", "context": "import", "confidence": "EXTRACTED", "source_file": "C:\\Users\\ASUS\\Desktop\\DokLynk\\DokLynk Web\\src\\components\\PostCard.tsx", "source_location": "L17", "weight": 1.0}, {"source": "c_users_asus_desktop_doklynk_doklynk_web_src_components_postcard_tsx", "target": "context_authcontext_useauth", "relation": "imports", "context": "import", "confidence": "EXTRACTED", "source_file": "C:\\Users\\ASUS\\Desktop\\DokLynk\\DokLynk Web\\src\\components\\PostCard.tsx", "source_location": "L17", "weight": 1.0}, {"source": "c_users_asus_desktop_doklynk_doklynk_web_src_components_postcard_tsx", "target": "c_users_asus_desktop_doklynk_doklynk_web_src_components_ui_toast_tsx", "relation": "imports_from", "context": "import", "confidence": "EXTRACTED", "source_file": "C:\\Users\\ASUS\\Desktop\\DokLynk\\DokLynk Web\\src\\components\\PostCard.tsx", "source_location": "L18", "weight": 1.0}, {"source": "c_users_asus_desktop_doklynk_doklynk_web_src_components_postcard_tsx", "target": "ui_toast_usetoast", "relation": "imports", "context": "import", "confidence": "EXTRACTED", "source_file": "C:\\Users\\ASUS\\Desktop\\DokLynk\\DokLynk Web\\src\\components\\PostCard.tsx", "source_location": "L18", "weight": 1.0}, {"source": "c_users_asus_desktop_doklynk_doklynk_web_src_components_postcard_tsx", "target": "c_users_asus_desktop_doklynk_doklynk_web_src_lib_utils_ts", "relation": "imports_from", "context": "import", "confidence": "EXTRACTED", "source_file": "C:\\Users\\ASUS\\Desktop\\DokLynk\\DokLynk Web\\src\\components\\PostCard.tsx", "source_location": "L19", "weight": 1.0}, {"source": "c_users_asus_desktop_doklynk_doklynk_web_src_components_postcard_tsx", "target": "lib_utils_cn", "relation": "imports", "context": "import", "confidence": "EXTRACTED", "source_file": "C:\\Users\\ASUS\\Desktop\\DokLynk\\DokLynk Web\\src\\components\\PostCard.tsx", "source_location": "L19", "weight": 1.0}, {"source": "c_users_asus_desktop_doklynk_doklynk_web_src_components_postcard_tsx", "target": "lib_utils_timeago", "relation": "imports", "context": "import", "confidence": "EXTRACTED", "source_file": "C:\\Users\\ASUS\\Desktop\\DokLynk\\DokLynk Web\\src\\components\\PostCard.tsx", "source_location": "L19", "weight": 1.0}, {"source": "c_users_asus_desktop_doklynk_doklynk_web_src_components_postcard_tsx", "target": "lib_utils_timeagolong", "relation": "imports", "context": "import", "confidence": "EXTRACTED", "source_file": "C:\\Users\\ASUS\\Desktop\\DokLynk\\DokLynk Web\\src\\components\\PostCard.tsx", "source_location": "L19", "weight": 1.0}, {"source": "c_users_asus_desktop_doklynk_doklynk_web_src_components_postcard_tsx", "target": "lib_utils_compact", "relation": "imports", "context": "import", "confidence": "EXTRACTED", "source_file": "C:\\Users\\ASUS\\Desktop\\DokLynk\\DokLynk Web\\src\\components\\PostCard.tsx", "source_location": "L19", "weight": 1.0}, {"source": "c_users_asus_desktop_doklynk_doklynk_web_src_components_postcard_tsx", "target": "lib_utils_rolelabel", "relation": "imports", "context": "import", "confidence": "EXTRACTED", "source_file": "C:\\Users\\ASUS\\Desktop\\DokLynk\\DokLynk Web\\src\\components\\PostCard.tsx", "source_location": "L19", "weight": 1.0}, {"source": "c_users_asus_desktop_doklynk_doklynk_web_src_components_postcard_tsx", "target": "c_users_asus_desktop_doklynk_doklynk_web_src_lib_api_ts", "relation": "imports_from", "context": "import", "confidence": "EXTRACTED", "source_file": "C:\\Users\\ASUS\\Desktop\\DokLynk\\DokLynk Web\\src\\components\\PostCard.tsx", "source_location": "L20", "weight": 1.0}, {"source": "c_users_asus_desktop_doklynk_doklynk_web_src_components_postcard_tsx", "target": "lib_api_dok", "relation": "imports", "context": "import", "confidence": "EXTRACTED", "source_file": "C:\\Users\\ASUS\\Desktop\\DokLynk\\DokLynk Web\\src\\components\\PostCard.tsx", "source_location": "L20", "weight": 1.0}, {"source": "c_users_asus_desktop_doklynk_doklynk_web_src_components_postcard_tsx", "target": "components_postcard_postcard", "relation": "contains", "confidence": "EXTRACTED", "source_file": "C:\\Users\\ASUS\\Desktop\\DokLynk\\DokLynk Web\\src\\components\\PostCard.tsx", "source_location": "L28", "weight": 1.0}, {"source": "c_users_asus_desktop_doklynk_doklynk_web_src_components_postcard_tsx", "target": "components_postcard_rendercontent", "relation": "contains", "confidence": "EXTRACTED", "source_file": "C:\\Users\\ASUS\\Desktop\\DokLynk\\DokLynk Web\\src\\components\\PostCard.tsx", "source_location": "L340", "weight": 1.0}, {"source": "components_postcard_postcard", "target": "components_postcard_rendercontent", "relation": "calls", "context": "call", "confidence": "EXTRACTED", "source_file": "C:\\Users\\ASUS\\Desktop\\DokLynk\\DokLynk Web\\src\\components\\PostCard.tsx", "source_location": "L210", "weight": 1.0}], "raw_calls": [{"caller_nid": "components_postcard_postcard", "callee": "useNavigate", "is_member_call": false, "source_file": "C:\\Users\\ASUS\\Desktop\\DokLynk\\DokLynk Web\\src\\components\\PostCard.tsx", "source_location": "L29"}, {"caller_nid": "components_postcard_postcard", "callee": "useToast", "is_member_call": false, "source_file": "C:\\Users\\ASUS\\Desktop\\DokLynk\\DokLynk Web\\src\\components\\PostCard.tsx", "source_location": "L30"}, {"caller_nid": "components_postcard_postcard", "callee": "useAuth", "is_member_call": false, "source_file": "C:\\Users\\ASUS\\Desktop\\DokLynk\\DokLynk Web\\src\\components\\PostCard.tsx", "source_location": "L31"}, {"caller_nid": "components_postcard_postcard", "callee": "Boolean", "is_member_call": false, "source_file": "C:\\Users\\ASUS\\Desktop\\DokLynk\\DokLynk Web\\src\\components\\PostCard.tsx", "source_location": "L34"}, {"caller_nid": "components_postcard_postcard", "callee": "useState", "is_member_call": false, "source_file": "C:\\Users\\ASUS\\Desktop\\DokLynk\\DokLynk Web\\src\\components\\PostCard.tsx", "source_location": "L37"}, {"caller_nid": "components_postcard_postcard", "callee": "useState", "is_member_call": false, "source_file": "C:\\Users\\ASUS\\Desktop\\DokLynk\\DokLynk Web\\src\\components\\PostCard.tsx", "source_location": "L38"}, {"caller_nid": "components_postcard_postcard", "callee": "useState", "is_member_call": false, "source_file": "C:\\Users\\ASUS\\Desktop\\DokLynk\\DokLynk Web\\src\\components\\PostCard.tsx", "source_location": "L39"}, {"caller_nid": "components_postcard_postcard", "callee": "useState", "is_member_call": false, "source_file": "C:\\Users\\ASUS\\Desktop\\DokLynk\\DokLynk Web\\src\\components\\PostCard.tsx", "source_location": "L40"}, {"caller_nid": "components_postcard_postcard", "callee": "Boolean", "is_member_call": false, "source_file": "C:\\Users\\ASUS\\Desktop\\DokLynk\\DokLynk Web\\src\\components\\PostCard.tsx", "source_location": "L40"}, {"caller_nid": "components_postcard_postcard", "callee": "useState", "is_member_call": false, "source_file": "C:\\Users\\ASUS\\Desktop\\DokLynk\\DokLynk Web\\src\\components\\PostCard.tsx", "source_location": "L41"}, {"caller_nid": "components_postcard_postcard", "callee": "useState", "is_member_call": false, "source_file": "C:\\Users\\ASUS\\Desktop\\DokLynk\\DokLynk Web\\src\\components\\PostCard.tsx", "source_location": "L42"}, {"caller_nid": "components_postcard_postcard", "callee": "Boolean", "is_member_call": false, "source_file": "C:\\Users\\ASUS\\Desktop\\DokLynk\\DokLynk Web\\src\\components\\PostCard.tsx", "source_location": "L42"}, {"caller_nid": "components_postcard_postcard", "callee": "useState", "is_member_call": false, "source_file": "C:\\Users\\ASUS\\Desktop\\DokLynk\\DokLynk Web\\src\\components\\PostCard.tsx", "source_location": "L45"}, {"caller_nid": "components_postcard_postcard", "callee": "useState", "is_member_call": false, "source_file": "C:\\Users\\ASUS\\Desktop\\DokLynk\\DokLynk Web\\src\\components\\PostCard.tsx", "source_location": "L46"}, {"caller_nid": "components_postcard_postcard", "callee": "useState", "is_member_call": false, "source_file": "C:\\Users\\ASUS\\Desktop\\DokLynk\\DokLynk Web\\src\\components\\PostCard.tsx", "source_location": "L47"}, {"caller_nid": "components_postcard_postcard", "callee": "useState", "is_member_call": false, "source_file": "C:\\Users\\ASUS\\Desktop\\DokLynk\\DokLynk Web\\src\\components\\PostCard.tsx", "source_location": "L48"}, {"caller_nid": "components_postcard_postcard", "callee": "useState", "is_member_call": false, "source_file": "C:\\Users\\ASUS\\Desktop\\DokLynk\\DokLynk Web\\src\\components\\PostCard.tsx", "source_location": "L49"}, {"caller_nid": "components_postcard_postcard", "callee": "useState", "is_member_call": false, "source_file": "C:\\Users\\ASUS\\Desktop\\DokLynk\\DokLynk Web\\src\\components\\PostCard.tsx", "source_location": "L50"}, {"caller_nid": "components_postcard_postcard", "callee": "useState", "is_member_call": false, "source_file": "C:\\Users\\ASUS\\Desktop\\DokLynk\\DokLynk Web\\src\\components\\PostCard.tsx", "source_location": "L51"}, {"caller_nid": "components_postcard_postcard", "callee": "useState", "is_member_call": false, "source_file": "C:\\Users\\ASUS\\Desktop\\DokLynk\\DokLynk Web\\src\\components\\PostCard.tsx", "source_location": "L52"}, {"caller_nid": "components_postcard_postcard", "callee": "useState", "is_member_call": false, "source_file": "C:\\Users\\ASUS\\Desktop\\DokLynk\\DokLynk Web\\src\\components\\PostCard.tsx", "source_location": "L55"}, {"caller_nid": "components_postcard_postcard", "callee": "useState", "is_member_call": false, "source_file": "C:\\Users\\ASUS\\Desktop\\DokLynk\\DokLynk Web\\src\\components\\PostCard.tsx", "source_location": "L56"}, {"caller_nid": "components_postcard_postcard", "callee": "useState", "is_member_call": false, "source_file": "C:\\Users\\ASUS\\Desktop\\DokLynk\\DokLynk Web\\src\\components\\PostCard.tsx", "source_location": "L57"}, {"caller_nid": "components_postcard_postcard", "callee": "useRef", "is_member_call": false, "source_file": "C:\\Users\\ASUS\\Desktop\\DokLynk\\DokLynk Web\\src\\components\\PostCard.tsx", "source_location": "L58"}, {"caller_nid": "components_postcard_postcard", "callee": "useEffect", "is_member_call": false, "source_file": "C:\\Users\\ASUS\\Desktop\\DokLynk\\DokLynk Web\\src\\components\\PostCard.tsx", "source_location": "L60"}, {"caller_nid": "components_postcard_postcard", "callee": "canEditPost", "is_member_call": false, "source_file": "C:\\Users\\ASUS\\Desktop\\DokLynk\\DokLynk Web\\src\\components\\PostCard.tsx", "source_location": "L173"}, {"caller_nid": "components_postcard_postcard", "callee": "cn", "is_member_call": false, "source_file": "C:\\Users\\ASUS\\Desktop\\DokLynk\\DokLynk Web\\src\\components\\PostCard.tsx", "source_location": "L176"}, {"caller_nid": "components_postcard_postcard", "callee": "roleLabel", "is_member_call": false, "source_file": "C:\\Users\\ASUS\\Desktop\\DokLynk\\DokLynk Web\\src\\components\\PostCard.tsx", "source_location": "L192"}, {"caller_nid": "components_postcard_postcard", "callee": "toLocaleString", "is_member_call": true, "source_file": "C:\\Users\\ASUS\\Desktop\\DokLynk\\DokLynk Web\\src\\components\\PostCard.tsx", "source_location": "L196"}, {"caller_nid": "components_postcard_postcard", "callee": "timeAgo", "is_member_call": false, "source_file": "C:\\Users\\ASUS\\Desktop\\DokLynk\\DokLynk Web\\src\\components\\PostCard.tsx", "source_location": "L198"}, {"caller_nid": "components_postcard_postcard", "callee": "map", "is_member_call": true, "source_file": "C:\\Users\\ASUS\\Desktop\\DokLynk\\DokLynk Web\\src\\components\\PostCard.tsx", "source_location": "L213"}, {"caller_nid": "components_postcard_postcard", "callee": "map", "is_member_call": true, "source_file": "C:\\Users\\ASUS\\Desktop\\DokLynk\\DokLynk Web\\src\\components\\PostCard.tsx", "source_location": "L225"}, {"caller_nid": "components_postcard_postcard", "callee": "slice", "is_member_call": true, "source_file": "C:\\Users\\ASUS\\Desktop\\DokLynk\\DokLynk Web\\src\\components\\PostCard.tsx", "source_location": "L225"}, {"caller_nid": "components_postcard_postcard", "callee": "map", "is_member_call": true, "source_file": "C:\\Users\\ASUS\\Desktop\\DokLynk\\DokLynk Web\\src\\components\\PostCard.tsx", "source_location": "L249"}, {"caller_nid": "components_postcard_postcard", "callee": "slice", "is_member_call": true, "source_file": "C:\\Users\\ASUS\\Desktop\\DokLynk\\DokLynk Web\\src\\components\\PostCard.tsx", "source_location": "L249"}, {"caller_nid": "components_postcard_postcard", "callee": "compact", "is_member_call": false, "source_file": "C:\\Users\\ASUS\\Desktop\\DokLynk\\DokLynk Web\\src\\components\\PostCard.tsx", "source_location": "L253"}, {"caller_nid": "components_postcard_postcard", "callee": "compact", "is_member_call": false, "source_file": "C:\\Users\\ASUS\\Desktop\\DokLynk\\DokLynk Web\\src\\components\\PostCard.tsx", "source_location": "L258"}, {"caller_nid": "components_postcard_postcard", "callee": "compact", "is_member_call": false, "source_file": "C:\\Users\\ASUS\\Desktop\\DokLynk\\DokLynk Web\\src\\components\\PostCard.tsx", "source_location": "L268"}, {"caller_nid": "components_postcard_postcard", "callee": "compact", "is_member_call": false, "source_file": "C:\\Users\\ASUS\\Desktop\\DokLynk\\DokLynk Web\\src\\components\\PostCard.tsx", "source_location": "L271"}, {"caller_nid": "components_postcard_postcard", "callee": "cn", "is_member_call": false, "source_file": "C:\\Users\\ASUS\\Desktop\\DokLynk\\DokLynk Web\\src\\components\\PostCard.tsx", "source_location": "L274"}, {"caller_nid": "components_postcard_postcard", "callee": "cn", "is_member_call": false, "source_file": "C:\\Users\\ASUS\\Desktop\\DokLynk\\DokLynk Web\\src\\components\\PostCard.tsx", "source_location": "L275"}, {"caller_nid": "components_postcard_postcard", "callee": "timeAgoLong", "is_member_call": false, "source_file": "C:\\Users\\ASUS\\Desktop\\DokLynk\\DokLynk Web\\src\\components\\PostCard.tsx", "source_location": "L284"}, {"caller_nid": "components_postcard_postcard", "callee": "replace", "is_member_call": true, "source_file": "C:\\Users\\ASUS\\Desktop\\DokLynk\\DokLynk Web\\src\\components\\PostCard.tsx", "source_location": "L284"}, {"caller_nid": "components_postcard_postcard", "callee": "replace", "is_member_call": true, "source_file": "C:\\Users\\ASUS\\Desktop\\DokLynk\\DokLynk Web\\src\\components\\PostCard.tsx", "source_location": "L329"}, {"caller_nid": "components_postcard_rendercontent", "callee": "map", "is_member_call": true, "source_file": "C:\\Users\\ASUS\\Desktop\\DokLynk\\DokLynk Web\\src\\components\\PostCard.tsx", "source_location": "L341"}, {"caller_nid": "components_postcard_rendercontent", "callee": "split", "is_member_call": true, "source_file": "C:\\Users\\ASUS\\Desktop\\DokLynk\\DokLynk Web\\src\\components\\PostCard.tsx", "source_location": "L341"}]}